pymetdecoder/__init__.py
pymetdecoder/code_tables.py
pymetdecoder/conversion.py
pymetdecoder/synop/__init__.py
pymetdecoder/synop/observations.py
pymetdecoder_wmo-0.1.14.dist-info/LICENSE.md
pymetdecoder_wmo-0.1.14.dist-info/METADATA
pymetdecoder_wmo-0.1.14.dist-info/WHEEL
pymetdecoder_wmo-0.1.14.dist-info/top_level.txt
pymetdecoder_wmo-0.1.14.dist-info/RECORD
