Metadata-Version: 2.1
Name: pymetdecoder-wmo
Version: 0.1.14
Summary: Python module to decode/encode met reports e.g. SYNOPs, adapted for use with the synop2bufr module.
Home-page: https://github.com/wmo-im/pymetdecoder
Author: Tim Barnes
Author-email: tdba@bas.ac.uk
License: Open Government License v3.0
Classifier: Development Status :: 5 - Production/Stable
Classifier: Intended Audience :: Science/Research
Classifier: License :: Other/Proprietary License
Classifier: Programming Language :: Python :: 3
License-File: LICENSE.md
